{
  "+79819534340": {
    "cookies": [
      {
        "comment": null,
        "comment_url": null,
        "discard": false,
        "domain": ".login.vk.com",
        "domain_initial_dot": false,
        "domain_specified": true,
        "expires": null,
        "name": "h",
        "path": "/",
        "path_specified": true,
        "port": null,
        "port_specified": false,
        "rest": {
          "HttpOnly": null
        },
        "rfc2109": false,
        "secure": false,
        "value": "1",
        "version": 0
      },
      {
        "comment": null,
        "comment_url": null,
        "discard": false,
        "domain": ".login.vk.com",
        "domain_initial_dot": false,
        "domain_specified": true,
        "expires": null,
        "name": "l",
        "path": "/",
        "path_specified": true,
        "port": null,
        "port_specified": false,
        "rest": {
          "HttpOnly": null
        },
        "rfc2109": false,
        "secure": true,
        "value": "515007935",
        "version": 0
      },
      {
        "comment": null,
        "comment_url": null,
        "discard": false,
        "domain": ".login.vk.com",
        "domain_initial_dot": false,
        "domain_specified": true,
        "expires": null,
        "name": "p",
        "path": "/",
        "path_specified": true,
        "port": null,
        "port_specified": false,
        "rest": {
          "HttpOnly": null
        },
        "rfc2109": false,
        "secure": true,
        "value": "918a988aa4551bc2541a89b76ed807a7a5f916b1d145731a581d2",
        "version": 0
      },
      {
        "comment": null,
        "comment_url": null,
        "discard": false,
        "domain": ".login.vk.com",
        "domain_initial_dot": false,
        "domain_specified": true,
        "expires": null,
        "name": "s",
        "path": "/",
        "path_specified": true,
        "port": null,
        "port_specified": false,
        "rest": {
          "HttpOnly": null
        },
        "rfc2109": false,
        "secure": true,
        "value": "1",
        "version": 0
      },
      {
        "comment": null,
        "comment_url": null,
        "discard": false,
        "domain": ".vk.com",
        "domain_initial_dot": true,
        "domain_specified": true,
        "expires": null,
        "name": "remixlang",
        "path": "/",
        "path_specified": true,
        "port": null,
        "port_specified": false,
        "rest": {},
        "rfc2109": false,
        "secure": false,
        "value": "0",
        "version": 0
      },
      {
        "comment": null,
        "comment_url": null,
        "discard": false,
        "domain": ".vk.com",
        "domain_initial_dot": true,
        "domain_specified": true,
        "expires": null,
        "name": "remixsid",
        "path": "/",
        "path_specified": true,
        "port": null,
        "port_specified": false,
        "rest": {
          "HttpOnly": null
        },
        "rfc2109": false,
        "secure": true,
        "value": "0f955ee3f870fcc32c0314a3a2e037691a262d24cc8bc0563e22f",
        "version": 0
      },
      {
        "comment": null,
        "comment_url": null,
        "discard": false,
        "domain": ".vk.com",
        "domain_initial_dot": true,
        "domain_specified": true,
        "expires": null,
        "name": "remixstid",
        "path": "/",
        "path_specified": true,
        "port": null,
        "port_specified": false,
        "rest": {},
        "rfc2109": false,
        "secure": false,
        "value": "1578806579_52eb0bd7352e9d5be5",
        "version": 0
      },
      {
        "comment": null,
        "comment_url": null,
        "discard": false,
        "domain": ".vk.com",
        "domain_initial_dot": true,
        "domain_specified": true,
        "expires": null,
        "name": "remixusid",
        "path": "/",
        "path_specified": true,
        "port": null,
        "port_specified": false,
        "rest": {
          "HttpOnly": null
        },
        "rfc2109": false,
        "secure": true,
        "value": "MmQwMzVlODcxNDI5MzM1ODE0OWZjNWJl",
        "version": 0
      }
    ],
    "token": {
      "app6222115": {
        "scope_140492255": {
          "access_token": "d513111b2d4bbd237ffc7801b3b537b449d26123a1c5de0fc7ab72269739ad2b4b7e88bac1444be61682f",
          "expires_in": "0",
          "user_id": "515007935"
        }
      }
    }
  }
}